extended_configparser/__init__.py
extended_configparser/interpolator.py
extended_configparser/matcher.py
extended_configparser/parser.py
extended_configparser/configuration/__init__.py
extended_configparser/configuration/configuration.py
extended_configparser/configuration/entries/__init__.py
extended_configparser/configuration/entries/base.py
extended_configparser/configuration/entries/confirmation.py
extended_configparser/configuration/entries/section.py
extended_configparser/configuration/entries/selection.py
extended_configparser-1.2.2.dist-info/METADATA
extended_configparser-1.2.2.dist-info/WHEEL
extended_configparser-1.2.2.dist-info/licenses/LICENSE
extended_configparser-1.2.2.dist-info/RECORD
