Metadata-Version: 2.3
Name: extended-configparser
Version: 1.2.2
Summary: Extended config parser.
Project-URL: Homepage, https://github.com/vschroeter/extended-configparser
Project-URL: Issues, https://github.com/vschroeter/extended-configparser/issues
Author-email: Valentin Schröter <vasc9380@th-wildau.de>
License-File: LICENSE
Classifier: Programming Language :: Python :: 3
Requires-Python: >=3.8
Provides-Extra: cli
Requires-Dist: inquirerpy; extra == 'cli'
Provides-Extra: dev
Requires-Dist: black; extra == 'dev'
Requires-Dist: flake8; extra == 'dev'
Requires-Dist: inquirerpy; extra == 'dev'
Requires-Dist: mypy; extra == 'dev'
Requires-Dist: nox; extra == 'dev'
Requires-Dist: pre-commit; extra == 'dev'
Requires-Dist: pytest; extra == 'dev'
Requires-Dist: pytest-cov; extra == 'dev'
Requires-Dist: pytest-datadir; extra == 'dev'
Requires-Dist: pytest-mock; extra == 'dev'
Provides-Extra: test
Requires-Dist: nox; extra == 'test'
Requires-Dist: pytest; extra == 'test'
Requires-Dist: pytest-datadir; extra == 'test'
Requires-Dist: pytest-mock; extra == 'test'
